azure_recommendations_3/__init__.py
azure_recommendations_3/recommendation/__init__.py
azure_recommendations_3/recommendation/advisor_recommendations.py
azure_recommendations_3/recommendation/network_recommendations.py
azure_recommendations_3/recommendation/utils.py
azure_recommendations_3/recommendation/vm_recommendations.py
azure_recommendations_3-0.1.4.dist-info/LICENCE
azure_recommendations_3-0.1.4.dist-info/METADATA
azure_recommendations_3-0.1.4.dist-info/WHEEL
azure_recommendations_3-0.1.4.dist-info/top_level.txt
azure_recommendations_3-0.1.4.dist-info/RECORD
